setup.py
simplerun/__init__.py
simplerun/compat.py
simplerun/simplerun.py
simplerun.egg-info/PKG-INFO
simplerun.egg-info/SOURCES.txt
simplerun.egg-info/dependency_links.txt
simplerun.egg-info/not-zip-safe
simplerun.egg-info/top_level.txt